flatn/__init__.py
flatn/_flat.py
flatn/flatter
flatn-0.3.2.dist-info/licenses/LICENSE
flatn-0.3.2.dist-info/METADATA
flatn-0.3.2.dist-info/WHEEL
flatn-0.3.2.dist-info/top_level.txt
flatn-0.3.2.dist-info/RECORD
