Metadata-Version: 2.4
Name: flatn
Version: 0.3.2
Summary: A Python wrapper for the flatter LLL-reduction library.
Author: Mathias Hall-Andersen
Author-email: Mathias Hall-Andersen <mathias@hall-andersen.dk>
License-Expression: GPL-3.0
Project-URL: Homepage, https://github.com/zksecurity/flatn
Platform: linux
Platform: darwin
Requires-Python: >=3.4
License-File: LICENSE
Dynamic: author
Dynamic: license-file
Dynamic: platform
Dynamic: requires-python
